artella/__init__.py
artella/dccs/__init__.py
artella/dccs/standalone/__init__.py
artella/dccs/standalone/__version__.py
artella/dccs/standalone/_version.py
artella/dccs/standalone/dcc.py
artella/dccs/standalone/plugin.py
tests/__init__.py
tests/test_client.py
artella_dccs_standalone-1.0.3.dist-info/METADATA
artella_dccs_standalone-1.0.3.dist-info/WHEEL
artella_dccs_standalone-1.0.3.dist-info/top_level.txt
artella_dccs_standalone-1.0.3.dist-info/RECORD
